{
  "distribution":[
    {
      "percent":"1.76494354307",
      "sample":"S1"
    },
    {
      "percent":"0.774140546006",
      "sample":"S10"
    },
    {
      "percent":"0.358088417363",
      "sample":"S11"
    },
    {
      "percent":"0.127386780695",
      "sample":"S12"
    },
    {
      "percent":"0.0103093964421",
      "sample":"S13"
    },
    {
      "percent":"0.0373644604198",
      "sample":"S14"
    },
    {
      "percent":"0.800108673504",
      "sample":"S15"
    },
    {
      "percent":"1.77093184439",
      "sample":"S16"
    },
    {
      "percent":"0.113636363636",
      "sample":"S17"
    },
    {
      "percent":"0.371722313385",
      "sample":"S18"
    },
    {
      "percent":"0.644598590877",
      "sample":"S19"
    },
    {
      "percent":"0.58838124269",
      "sample":"S2"
    },
    {
      "percent":"0.382803297998",
      "sample":"S20"
    },
    {
      "percent":"0.609232737003",
      "sample":"S21"
    },
    {
      "percent":"0.761347769962",
      "sample":"S22"
    },
    {
      "percent":"1.33153495083",
      "sample":"S23"
    },
    {
      "percent":"0.385764585408",
      "sample":"S24"
    },
    {
      "percent":"0.157830128018",
      "sample":"S25"
    },
    {
      "percent":"0.0993779675365",
      "sample":"S26"
    },
    {
      "percent":"0.785393032154",
      "sample":"S27"
    },
    {
      "percent":"0.612196220815",
      "sample":"S28"
    },
    {
      "percent":"0.112040742088",
      "sample":"S29"
    },
    {
      "percent":"0.443980151476",
      "sample":"S3"
    },
    {
      "percent":"0.833792536518",
      "sample":"S30"
    },
    {
      "percent":"0.456310778061",
      "sample":"S31"
    },
    {
      "percent":"0.140626642835",
      "sample":"S32"
    },
    {
      "percent":"0.586153505862",
      "sample":"S33"
    },
    {
      "percent":"0.527520876358",
      "sample":"S34"
    },
    {
      "percent":"0.647393682331",
      "sample":"S35"
    },
    {
      "percent":"1.65828797549",
      "sample":"S36"
    },
    {
      "percent":"0.0106598443663",
      "sample":"S37"
    },
    {
      "percent":"0.286472634084",
      "sample":"S38"
    },
    {
      "percent":"2.24277938071",
      "sample":"S39"
    },
    {
      "percent":"1.33980426207",
      "sample":"S4"
    },
    {
      "percent":"0.86800592531",
      "sample":"S41"
    },
    {
      "percent":"0.122620739626",
      "sample":"S42"
    },
    {
      "percent":"0.0157004356871",
      "sample":"S43"
    },
    {
      "percent":"0.0401138716356",
      "sample":"S44"
    },
    {
      "percent":"0.13491528114",
      "sample":"S45"
    },
    {
      "percent":"0.0674085694676",
      "sample":"S46"
    },
    {
      "percent":"0.142010065275",
      "sample":"S47"
    },
    {
      "percent":"0.0527471031631",
      "sample":"S48"
    },
    {
      "percent":"1.28602689072",
      "sample":"S5"
    },
    {
      "percent":"0.0379190050053",
      "sample":"S50"
    },
    {
      "percent":"0.320270610673",
      "sample":"S51"
    },
    {
      "percent":"0.248518791983",
      "sample":"S52"
    },
    {
      "percent":"2.66804362986",
      "sample":"S54"
    },
    {
      "percent":"0.778434045131",
      "sample":"S55"
    },
    {
      "percent":"4.01784416868",
      "sample":"S57"
    },
    {
      "percent":"0.258589674402",
      "sample":"S58"
    },
    {
      "percent":"0.550747442958",
      "sample":"S59"
    },
    {
      "percent":"1.73927364381",
      "sample":"S6"
    },
    {
      "percent":"0.0837766514472",
      "sample":"S7"
    },
    {
      "percent":"0.135374362178",
      "sample":"S8"
    },
    {
      "percent":"0.018409002002",
      "sample":"S9"
    }
  ],
  "taxa":{
    "Class":"Betaproteobacteria",
    "Family":"Burkholderiaceae",
    "Genus":"Burkholderia",
    "Kingdom":"Bacteria",
    "Order":"Burkholderiales",
    "Phylum":"Proteobacteria",
    "Row":301
  }
}