{
  "distribution":[
    {
      "percent":"0.0284378159757",
      "sample":"S10"
    },
    {
      "percent":"0.207261735077",
      "sample":"S12"
    },
    {
      "percent":"0.0441013070024",
      "sample":"S13"
    },
    {
      "percent":"0.047079220129",
      "sample":"S14"
    },
    {
      "percent":"0.0149426068057",
      "sample":"S15"
    },
    {
      "percent":"0.0340696929639",
      "sample":"S19"
    },
    {
      "percent":"0.0861843823453",
      "sample":"S3"
    },
    {
      "percent":"0.0340303891375",
      "sample":"S48"
    },
    {
      "percent":"0.15917563775",
      "sample":"S7"
    }
  ],
  "taxa":{
    "Class":"Alphaproteobacteria",
    "Family":"Phyllobacteriaceae",
    "Genus":"Unknown",
    "Kingdom":"Bacteria",
    "Order":"Rhizobiales",
    "Phylum":"Proteobacteria",
    "Row":241
  }
}