{
  "distribution":[
    {
      "percent":"0.0318965700555",
      "sample":"S1"
    },
    {
      "percent":"0.251727334007",
      "sample":"S10"
    },
    {
      "percent":"0.803794213444",
      "sample":"S11"
    },
    {
      "percent":"0.453083792959",
      "sample":"S12"
    },
    {
      "percent":"0.396911763021",
      "sample":"S13"
    },
    {
      "percent":"0.0328807251694",
      "sample":"S14"
    },
    {
      "percent":"0.081505128031",
      "sample":"S15"
    },
    {
      "percent":"0.0103639025275",
      "sample":"S16"
    },
    {
      "percent":"0.0324675324675",
      "sample":"S17"
    },
    {
      "percent":"0.0401861960417",
      "sample":"S18"
    },
    {
      "percent":"0.926695648619",
      "sample":"S19"
    },
    {
      "percent":"0.0496225144437",
      "sample":"S2"
    },
    {
      "percent":"0.125147232038",
      "sample":"S20"
    },
    {
      "percent":"0.0276614241682",
      "sample":"S22"
    },
    {
      "percent":"0.0350695077644",
      "sample":"S24"
    },
    {
      "percent":"0.253307612868",
      "sample":"S25"
    },
    {
      "percent":"0.0331259891788",
      "sample":"S26"
    },
    {
      "percent":"0.132577028932",
      "sample":"S27"
    },
    {
      "percent":"0.0174608948709",
      "sample":"S29"
    },
    {
      "percent":"0.0600679028467",
      "sample":"S3"
    },
    {
      "percent":"0.0379407221384",
      "sample":"S30"
    },
    {
      "percent":"0.122226895174",
      "sample":"S32"
    },
    {
      "percent":"0.0479245004792",
      "sample":"S33"
    },
    {
      "percent":"0.0875460177786",
      "sample":"S34"
    },
    {
      "percent":"0.0186032667336",
      "sample":"S35"
    },
    {
      "percent":"2.4550976573",
      "sample":"S36"
    },
    {
      "percent":"0.218508849608",
      "sample":"S4"
    },
    {
      "percent":"0.0367354435805",
      "sample":"S40"
    },
    {
      "percent":"0.061310369813",
      "sample":"S42"
    },
    {
      "percent":"0.0431761981395",
      "sample":"S43"
    },
    {
      "percent":"0.137163561077",
      "sample":"S44"
    },
    {
      "percent":"0.0257926272767",
      "sample":"S45"
    },
    {
      "percent":"0.0224226418855",
      "sample":"S47"
    },
    {
      "percent":"0.0119106361981",
      "sample":"S48"
    },
    {
      "percent":"0.101805586435",
      "sample":"S5"
    },
    {
      "percent":"0.0719709237468",
      "sample":"S51"
    },
    {
      "percent":"0.381782492031",
      "sample":"S52"
    },
    {
      "percent":"0.10532285506",
      "sample":"S53"
    },
    {
      "percent":"0.198559511959",
      "sample":"S54"
    },
    {
      "percent":"2.15568601238",
      "sample":"S57"
    },
    {
      "percent":"0.856718834323",
      "sample":"S58"
    },
    {
      "percent":"1.914503016",
      "sample":"S59"
    },
    {
      "percent":"0.0307899409979",
      "sample":"S6"
    },
    {
      "percent":"0.293873599779",
      "sample":"S60"
    },
    {
      "percent":"0.757063238942",
      "sample":"S61"
    },
    {
      "percent":"0.754582500504",
      "sample":"S62"
    },
    {
      "percent":"0.102626398023",
      "sample":"S7"
    },
    {
      "percent":"0.0138067515015",
      "sample":"S9"
    }
  ],
  "taxa":{
    "Class":"Sphingobacteriia",
    "Family":"Sphingobacteriaceae",
    "Genus":"Pedobacter",
    "Kingdom":"Bacteria",
    "Order":"Sphingobacteriales",
    "Phylum":"Bacteroidetes",
    "Row":412,
    "Species":"Pedobacter sp"
  }
}