[
  {
    "Class":"Acidobacteria (class)",
    "Kingdom":"Bacteria",
    "Percent":"0",
    "Phylum":"Acidobacteria"
  },
  {
    "Class":"Acidobacteriia",
    "Kingdom":"Bacteria",
    "Percent":"8.9225832662",
    "Phylum":"Acidobacteria"
  },
  {
    "Class":"Holophagae",
    "Kingdom":"Bacteria",
    "Percent":"0.81802970522",
    "Phylum":"Acidobacteria"
  },
  {
    "Class":"Solibacteres",
    "Kingdom":"Bacteria",
    "Percent":"0.0227230473672",
    "Phylum":"Acidobacteria"
  },
  {
    "Class":"Actinobacteria (class)",
    "Kingdom":"Bacteria",
    "Percent":"21.0649534866",
    "Phylum":"Actinobacteria"
  },
  {
    "Class":"Bacteroidetes (class)",
    "Kingdom":"Bacteria",
    "Percent":"0",
    "Phylum":"Bacteroidetes"
  },
  {
    "Class":"Bacteroidia",
    "Kingdom":"Bacteria",
    "Percent":"0.141846901747",
    "Phylum":"Bacteroidetes"
  },
  {
    "Class":"Cytophagia",
    "Kingdom":"Bacteria",
    "Percent":"3.93590723488",
    "Phylum":"Bacteroidetes"
  },
  {
    "Class":"Flavobacteriia",
    "Kingdom":"Bacteria",
    "Percent":"0.846949947324",
    "Phylum":"Bacteroidetes"
  },
  {
    "Class":"Sphingobacteriia",
    "Kingdom":"Bacteria",
    "Percent":"3.86291805243",
    "Phylum":"Bacteroidetes"
  },
  {
    "Class":"Chlamydiia",
    "Kingdom":"Bacteria",
    "Percent":"0",
    "Phylum":"Chlamydiae"
  },
  {
    "Class":"Anaerolineae",
    "Kingdom":"Bacteria",
    "Percent":"0",
    "Phylum":"Chloroflexi"
  },
  {
    "Class":"Caldilineae",
    "Kingdom":"Bacteria",
    "Percent":"0.025477356139",
    "Phylum":"Chloroflexi"
  },
  {
    "Class":"Chloroflexi (class)",
    "Kingdom":"Bacteria",
    "Percent":"0.30848258244",
    "Phylum":"Chloroflexi"
  },
  {
    "Class":"Ktedonobacteria",
    "Kingdom":"Bacteria",
    "Percent":"0.0241002017531",
    "Phylum":"Chloroflexi"
  },
  {
    "Class":"Thermomicrobia",
    "Kingdom":"Bacteria",
    "Percent":"0",
    "Phylum":"Chloroflexi"
  },
  {
    "Class":"Chrysiogenetes (class)",
    "Kingdom":"Bacteria",
    "Percent":"0",
    "Phylum":"Chrysiogenetes"
  },
  {
    "Class":"Cyanobacteria (class)",
    "Kingdom":"Bacteria",
    "Percent":"0",
    "Phylum":"Cyanobacteria"
  },
  {
    "Class":"Gloeobacteria",
    "Kingdom":"Bacteria",
    "Percent":"0",
    "Phylum":"Cyanobacteria"
  },
  {
    "Class":"Deferribacteres (class)",
    "Kingdom":"Bacteria",
    "Percent":"0.00206573157884",
    "Phylum":"Deferribacteres"
  },
  {
    "Class":"Deinococci",
    "Kingdom":"Bacteria",
    "Percent":"0.0364945912261",
    "Phylum":"Deinococcus-Thermus"
  },
  {
    "Class":"Fibrobacteria",
    "Kingdom":"Bacteria",
    "Percent":"0.0110172350871",
    "Phylum":"Fibrobacteres"
  },
  {
    "Class":"Bacilli",
    "Kingdom":"Bacteria",
    "Percent":"0.952990835038",
    "Phylum":"Firmicutes"
  },
  {
    "Class":"Clostridia",
    "Kingdom":"Bacteria",
    "Percent":"0.311236891212",
    "Phylum":"Firmicutes"
  },
  {
    "Class":"Erysipelotrichia",
    "Kingdom":"Bacteria",
    "Percent":"0",
    "Phylum":"Firmicutes"
  },
  {
    "Class":"Negativicutes",
    "Kingdom":"Bacteria",
    "Percent":"0",
    "Phylum":"Firmicutes"
  },
  {
    "Class":"Fusobacteriia",
    "Kingdom":"Bacteria",
    "Percent":"0",
    "Phylum":"Fusobacteria"
  },
  {
    "Class":"Gemmatimonadetes (class)",
    "Kingdom":"Bacteria",
    "Percent":"0.394554731558",
    "Phylum":"Gemmatimonadetes"
  },
  {
    "Class":"Ignavibacteria",
    "Kingdom":"Bacteria",
    "Percent":"0",
    "Phylum":"Ignavibacteriae"
  },
  {
    "Class":"Lentisphaeria",
    "Kingdom":"Bacteria",
    "Percent":"0",
    "Phylum":"Lentisphaerae"
  },
  {
    "Class":"Nitrospira (class)",
    "Kingdom":"Bacteria",
    "Percent":"0.0523318666639",
    "Phylum":"Nitrospirae"
  },
  {
    "Class":"Phycisphaerae",
    "Kingdom":"Bacteria",
    "Percent":"0",
    "Phylum":"Planctomycetes"
  },
  {
    "Class":"Planctomycetia",
    "Kingdom":"Bacteria",
    "Percent":"0.226541896479",
    "Phylum":"Planctomycetes"
  },
  {
    "Class":"Alphaproteobacteria",
    "Kingdom":"Bacteria",
    "Percent":"40.06279824",
    "Phylum":"Proteobacteria"
  },
  {
    "Class":"Betaproteobacteria",
    "Kingdom":"Bacteria",
    "Percent":"9.28684060127",
    "Phylum":"Proteobacteria"
  },
  {
    "Class":"Deltaproteobacteria",
    "Kingdom":"Bacteria",
    "Percent":"0.28989099823",
    "Phylum":"Proteobacteria"
  },
  {
    "Class":"Epsilonproteobacteria",
    "Kingdom":"Bacteria",
    "Percent":"0.0110172350871",
    "Phylum":"Proteobacteria"
  },
  {
    "Class":"Gammaproteobacteria",
    "Kingdom":"Bacteria",
    "Percent":"4.37728521556",
    "Phylum":"Proteobacteria"
  },
  {
    "Class":"Spirochaetia",
    "Kingdom":"Bacteria",
    "Percent":"0",
    "Phylum":"Spirochaetes"
  },
  {
    "Class":"TM7 (class)",
    "Kingdom":"Bacteria",
    "Percent":"0.076432068417",
    "Phylum":"TM7"
  },
  {
    "Class":"Mollicutes",
    "Kingdom":"Bacteria",
    "Percent":"0.000688577192946",
    "Phylum":"Tenericutes"
  },
  {
    "Class":"Opitutae",
    "Kingdom":"Bacteria",
    "Percent":"0.360125871911",
    "Phylum":"Verrucomicrobia"
  },
  {
    "Class":"Spartobacteria",
    "Kingdom":"Bacteria",
    "Percent":"0",
    "Phylum":"Verrucomicrobia"
  },
  {
    "Class":"Verrucomicrobiae",
    "Kingdom":"Bacteria",
    "Percent":"0.126009626309",
    "Phylum":"Verrucomicrobia"
  },
  {
    "Class":"No Hit",
    "Kingdom":"No Hit",
    "Percent":"3.44770600508",
    "Phylum":"No Hit"
  }
]