{
  "distribution":[
    {
      "percent":"0.0340230080592",
      "sample":"S1"
    },
    {
      "percent":"0.725690933603",
      "sample":"S10"
    },
    {
      "percent":"0.0457134149826",
      "sample":"S11"
    },
    {
      "percent":"0.050954712278",
      "sample":"S12"
    },
    {
      "percent":"0.335055384369",
      "sample":"S13"
    },
    {
      "percent":"0.510398529335",
      "sample":"S14"
    },
    {
      "percent":"0.820484955512",
      "sample":"S15"
    },
    {
      "percent":"0.115298415618",
      "sample":"S16"
    },
    {
      "percent":"0.15625",
      "sample":"S17"
    },
    {
      "percent":"0.0937677907639",
      "sample":"S18"
    },
    {
      "percent":"0.0722277490835",
      "sample":"S19"
    },
    {
      "percent":"0.0141778612696",
      "sample":"S2"
    },
    {
      "percent":"0.188947781704",
      "sample":"S20"
    },
    {
      "percent":"0.0942459482657",
      "sample":"S21"
    },
    {
      "percent":"0.052688426987",
      "sample":"S22"
    },
    {
      "percent":"0.0972381236179",
      "sample":"S23"
    },
    {
      "percent":"0.140278031058",
      "sample":"S24"
    },
    {
      "percent":"0.17341828881",
      "sample":"S25"
    },
    {
      "percent":"0.0276049909824",
      "sample":"S26"
    },
    {
      "percent":"0.13118490446",
      "sample":"S28"
    },
    {
      "percent":"0.0196435067297",
      "sample":"S29"
    },
    {
      "percent":"0.104465917994",
      "sample":"S3"
    },
    {
      "percent":"0.0141963353174",
      "sample":"S31"
    },
    {
      "percent":"0.0183997476606",
      "sample":"S32"
    },
    {
      "percent":"0.055297500553",
      "sample":"S33"
    },
    {
      "percent":"0.0246924665529",
      "sample":"S34"
    },
    {
      "percent":"0.0260445734271",
      "sample":"S35"
    },
    {
      "percent":"0.0284849837944",
      "sample":"S36"
    },
    {
      "percent":"0.0485081457075",
      "sample":"S38"
    },
    {
      "percent":"0.0989040056122",
      "sample":"S4"
    },
    {
      "percent":"0.0673483132309",
      "sample":"S40"
    },
    {
      "percent":"0.253601984227",
      "sample":"S42"
    },
    {
      "percent":"0.239431644228",
      "sample":"S43"
    },
    {
      "percent":"0.0905797101449",
      "sample":"S44"
    },
    {
      "percent":"0.112113209427",
      "sample":"S47"
    },
    {
      "percent":"0.153136751119",
      "sample":"S48"
    },
    {
      "percent":"0.0167873758933",
      "sample":"S49"
    },
    {
      "percent":"0.140421498531",
      "sample":"S5"
    },
    {
      "percent":"0.0439860458062",
      "sample":"S50"
    },
    {
      "percent":"0.010795638562",
      "sample":"S51"
    },
    {
      "percent":"0.0367308480567",
      "sample":"S54"
    },
    {
      "percent":"1.10555807966",
      "sample":"S55"
    },
    {
      "percent":"0.0129597470257",
      "sample":"S56"
    },
    {
      "percent":"0.123514196867",
      "sample":"S57"
    },
    {
      "percent":"0.0224860586436",
      "sample":"S58"
    },
    {
      "percent":"0.0104904274849",
      "sample":"S59"
    },
    {
      "percent":"0.158245975826",
      "sample":"S6"
    },
    {
      "percent":"0.077059252317",
      "sample":"S8"
    },
    {
      "percent":"0.0161078767517",
      "sample":"S9"
    }
  ],
  "taxa":{
    "Class":"Betaproteobacteria",
    "Family":"Burkholderiales (family)",
    "Genus":"Methylibium",
    "Kingdom":"Bacteria",
    "Order":"Burkholderiales",
    "Phylum":"Proteobacteria",
    "Row":960,
    "Species":"Methylibium sp"
  }
}