{
  "distribution":[
    {
      "percent":"0.0318965700555",
      "sample":"S1"
    },
    {
      "percent":"0.0442366026289",
      "sample":"S10"
    },
    {
      "percent":"0.110474086208",
      "sample":"S11"
    },
    {
      "percent":"0.0688577192946",
      "sample":"S12"
    },
    {
      "percent":"0.129049786049",
      "sample":"S15"
    },
    {
      "percent":"0.0479330491897",
      "sample":"S16"
    },
    {
      "percent":"0.018262987013",
      "sample":"S17"
    },
    {
      "percent":"0.0385117712066",
      "sample":"S18"
    },
    {
      "percent":"0.0981207157361",
      "sample":"S19"
    },
    {
      "percent":"0.0744337716655",
      "sample":"S2"
    },
    {
      "percent":"0.08588535532",
      "sample":"S20"
    },
    {
      "percent":"0.0579572696857",
      "sample":"S22"
    },
    {
      "percent":"0.0194852009898",
      "sample":"S25"
    },
    {
      "percent":"0.0570503146969",
      "sample":"S26"
    },
    {
      "percent":"0.338994428408",
      "sample":"S27"
    },
    {
      "percent":"0.0167333575846",
      "sample":"S29"
    },
    {
      "percent":"0.0313397753983",
      "sample":"S3"
    },
    {
      "percent":"0.0523943305721",
      "sample":"S30"
    },
    {
      "percent":"0.0243365748299",
      "sample":"S31"
    },
    {
      "percent":"0.0341709599411",
      "sample":"S32"
    },
    {
      "percent":"0.0482625482625",
      "sample":"S34"
    },
    {
      "percent":"0.130222867135",
      "sample":"S35"
    },
    {
      "percent":"0.133186545849",
      "sample":"S36"
    },
    {
      "percent":"0.0444160181928",
      "sample":"S37"
    },
    {
      "percent":"0.071302887767",
      "sample":"S4"
    },
    {
      "percent":"0.0139341749575",
      "sample":"S42"
    },
    {
      "percent":"0.0158723860164",
      "sample":"S45"
    },
    {
      "percent":"0.0124570232697",
      "sample":"S47"
    },
    {
      "percent":"0.0503177036404",
      "sample":"S5"
    },
    {
      "percent":"0.0143941847494",
      "sample":"S51"
    },
    {
      "percent":"0.0126060256803",
      "sample":"S52"
    },
    {
      "percent":"0.0271488876941",
      "sample":"S54"
    },
    {
      "percent":"0.033421488564",
      "sample":"S57"
    },
    {
      "percent":"0.267505900865",
      "sample":"S59"
    },
    {
      "percent":"0.0372343472533",
      "sample":"S6"
    },
    {
      "percent":"0.0458190148912",
      "sample":"S8"
    }
  ],
  "taxa":{
    "Class":"Alphaproteobacteria",
    "Family":"Beijerinckiaceae",
    "Genus":"Beijerinckia",
    "Kingdom":"Bacteria",
    "Order":"Rhizobiales",
    "Phylum":"Proteobacteria",
    "Row":638,
    "Species":"Beijerinckia indica"
  }
}