{
  "distribution":[
    {
      "percent":"0.0139341749575",
      "sample":"S42"
    },
    {
      "percent":"0.0117753267653",
      "sample":"S43"
    },
    {
      "percent":"0.0271739130435",
      "sample":"S44"
    },
    {
      "percent":"0.0743327340617",
      "sample":"S60"
    },
    {
      "percent":"0.0177185013369",
      "sample":"S61"
    }
  ],
  "taxa":{
    "Class":"Sphingobacteriia",
    "Family":"Sphingobacteriaceae",
    "Genus":"Pedobacter",
    "Kingdom":"Bacteria",
    "Order":"Sphingobacteriales",
    "Phylum":"Bacteroidetes",
    "Row":404,
    "Species":"Pedobacter composti"
  }
}