{
  "distribution":[
    {
      "percent":"0.0616667021073",
      "sample":"S1"
    },
    {
      "percent":"0.0410768452983",
      "sample":"S10"
    },
    {
      "percent":"0.0514275918554",
      "sample":"S11"
    },
    {
      "percent":"0.12394389473",
      "sample":"S12"
    },
    {
      "percent":"0.387175110826",
      "sample":"S13"
    },
    {
      "percent":"0.393821412825",
      "sample":"S14"
    },
    {
      "percent":"0.18474495687",
      "sample":"S15"
    },
    {
      "percent":"0.0129548781594",
      "sample":"S16"
    },
    {
      "percent":"0.0223214285714",
      "sample":"S17"
    },
    {
      "percent":"0.0200930980208",
      "sample":"S18"
    },
    {
      "percent":"0.162171738508",
      "sample":"S19"
    },
    {
      "percent":"0.0815227023004",
      "sample":"S2"
    },
    {
      "percent":"0.0392618767177",
      "sample":"S20"
    },
    {
      "percent":"0.015146670257",
      "sample":"S21"
    },
    {
      "percent":"0.140278031058",
      "sample":"S24"
    },
    {
      "percent":"0.163675688315",
      "sample":"S25"
    },
    {
      "percent":"0.0680923110898",
      "sample":"S26"
    },
    {
      "percent":"0.028529234074",
      "sample":"S27"
    },
    {
      "percent":"0.05092761004",
      "sample":"S29"
    },
    {
      "percent":"0.527552885871",
      "sample":"S3"
    },
    {
      "percent":"0.169829899096",
      "sample":"S30"
    },
    {
      "percent":"0.134055304384",
      "sample":"S32"
    },
    {
      "percent":"0.0808117087187",
      "sample":"S34"
    },
    {
      "percent":"0.081854373628",
      "sample":"S35"
    },
    {
      "percent":"0.204014073122",
      "sample":"S36"
    },
    {
      "percent":"0.0390860960097",
      "sample":"S37"
    },
    {
      "percent":"0.0118982244188",
      "sample":"S38"
    },
    {
      "percent":"0.0230009315377",
      "sample":"S4"
    },
    {
      "percent":"0.0224494377436",
      "sample":"S40"
    },
    {
      "percent":"0.0311858416279",
      "sample":"S41"
    },
    {
      "percent":"0.404091073768",
      "sample":"S42"
    },
    {
      "percent":"0.0785021784355",
      "sample":"S43"
    },
    {
      "percent":"0.0685817805383",
      "sample":"S44"
    },
    {
      "percent":"0.0575373993096",
      "sample":"S45"
    },
    {
      "percent":"0.0398624744631",
      "sample":"S47"
    },
    {
      "percent":"0.107195725783",
      "sample":"S48"
    },
    {
      "percent":"0.0983260588038",
      "sample":"S49"
    },
    {
      "percent":"0.0514878827949",
      "sample":"S5"
    },
    {
      "percent":"0.829667829516",
      "sample":"S50"
    },
    {
      "percent":"0.0503796466228",
      "sample":"S51"
    },
    {
      "percent":"0.030614633795",
      "sample":"S52"
    },
    {
      "percent":"0.0947549413637",
      "sample":"S54"
    },
    {
      "percent":"0.093896713615",
      "sample":"S55"
    },
    {
      "percent":"0.0622067857235",
      "sample":"S56"
    },
    {
      "percent":"0.0101717573891",
      "sample":"S57"
    },
    {
      "percent":"0.155153804641",
      "sample":"S58"
    },
    {
      "percent":"0.0314712824548",
      "sample":"S59"
    },
    {
      "percent":"0.0336541215558",
      "sample":"S6"
    },
    {
      "percent":"0.0128861827905",
      "sample":"S61"
    },
    {
      "percent":"0.0480329723113",
      "sample":"S62"
    },
    {
      "percent":"0.406316759519",
      "sample":"S7"
    },
    {
      "percent":"0.0541497448714",
      "sample":"S8"
    },
    {
      "percent":"0.303748533033",
      "sample":"S9"
    }
  ],
  "taxa":{
    "Class":"Alphaproteobacteria",
    "Family":"Rhizobiaceae",
    "Genus":"Agrobacterium",
    "Kingdom":"Bacteria",
    "Order":"Rhizobiales",
    "Phylum":"Proteobacteria",
    "Row":342
  }
}